README.md
setup.py
django_vue_rollup/__init__.py
django_vue_rollup/rollup.config.js
django_vue_rollup.egg-info/PKG-INFO
django_vue_rollup.egg-info/SOURCES.txt
django_vue_rollup.egg-info/dependency_links.txt
django_vue_rollup.egg-info/requires.txt
django_vue_rollup.egg-info/top_level.txt
django_vue_rollup/npm_prefix/package-lock.json