Metadata-Version: 2.1
Name: django-vue-rollup
Version: 0.1.0
Summary: A django-compressor filter to compile .vue files using rollup
Home-page: https://github.com/codingcatgirl/django-vue-rollup
Author: Laura Klünder
Author-email: laura@codingcatgirl.de
License: Apache
Platform: UNKNOWN
Classifier: Development Status :: 3 - Alpha
Classifier: Environment :: Web Environment
Classifier: Intended Audience :: Developers
Classifier: License :: OSI Approved :: Apache Software License
Classifier: Programming Language :: Python
Classifier: Programming Language :: Python :: 3
Classifier: Framework :: Django
Classifier: Framework :: Django :: 2.0
Classifier: Framework :: Django :: 2.1
Classifier: Framework :: Django :: 2.2
Classifier: Framework :: Django :: 3.0
